README.md
setup.cfg
setup.py
banyanclient/__init__.py
banyanclient/api_client.py
banyanclient/configuration.py
banyanclient/exceptions.py
banyanclient/rest.py
banyanclient/schemas.py
banyanclient.egg-info/PKG-INFO
banyanclient.egg-info/SOURCES.txt
banyanclient.egg-info/dependency_links.txt
banyanclient.egg-info/requires.txt
banyanclient.egg-info/top_level.txt
banyanclient/apis/__init__.py
banyanclient/apis/path_to_api.py
banyanclient/apis/tag_to_api.py
banyanclient/apis/paths/__init__.py
banyanclient/apis/paths/service_tunnel_id_security_policy.py
banyanclient/apis/paths/service_tunnel_id_security_policy_policy_id.py
banyanclient/apis/paths/v1_access_tiers_stats.py
banyanclient/apis/paths/v1_audit_logs.py
banyanclient/apis/paths/v1_delete_device.py
banyanclient/apis/paths/v1_delete_registered_service.py
banyanclient/apis/paths/v1_delete_security_attach_policy.py
banyanclient/apis/paths/v1_delete_security_policy.py
banyanclient/apis/paths/v1_delete_security_role.py
banyanclient/apis/paths/v1_device_id_token.py
banyanclient/apis/paths/v1_devices.py
banyanclient/apis/paths/v1_devices_stats.py
banyanclient/apis/paths/v1_disable_registered_service.py
banyanclient/apis/paths/v1_disable_security_role.py
banyanclient/apis/paths/v1_enable_registered_service.py
banyanclient/apis/paths/v1_enable_security_role.py
banyanclient/apis/paths/v1_enduser_devices.py
banyanclient/apis/paths/v1_enduser_devices_data.py
banyanclient/apis/paths/v1_endusers.py
banyanclient/apis/paths/v1_endusers_csv.py
banyanclient/apis/paths/v1_endusers_stats.py
banyanclient/apis/paths/v1_event_types.py
banyanclient/apis/paths/v1_events.py
banyanclient/apis/paths/v1_events_count.py
banyanclient/apis/paths/v1_events_feed.py
banyanclient/apis/paths/v1_insert_registered_service.py
banyanclient/apis/paths/v1_insert_saasapp.py
banyanclient/apis/paths/v1_insert_security_attach_policy.py
banyanclient/apis/paths/v1_insert_security_policy.py
banyanclient/apis/paths/v1_insert_security_role.py
banyanclient/apis/paths/v1_mdm_device_info.py
banyanclient/apis/paths/v1_mdm_insert_devices.py
banyanclient/apis/paths/v1_mdm_update_device.py
banyanclient/apis/paths/v1_one_click_support_bundle.py
