Metadata-Version: 2.1
Name: banyanclient
Version: 0.0.1
Summary: Banyan Rest APIs
Home-page: 
Author: OpenAPI Generator community
Author-email: team@openapitools.org
Keywords: OpenAPI,OpenAPI-Generator,Banyan Rest APIs
Requires-Python: >=3.7
